pycgs/__init__.py
pycgs/cgs/__init__.py
pycgs/cgs/algorithms.py
pycgs/cgs/primary_term_extractor.py
pycgs/types.py
pycgs-1.1.0.dist-info/LICENSE
pycgs-1.1.0.dist-info/METADATA
pycgs-1.1.0.dist-info/WHEEL
pycgs-1.1.0.dist-info/RECORD
