Metadata-Version: 2.1
Name: pycgs
Version: 1.1.0
Summary: Python implementation of the Coreference-based Graph Search (CGS) algorithm.
License: Apache-2.0
Author: YANG Zijie
Author-email: yangzijie@westlake.edu.cn
Requires-Python: >=3.11,<4.0
Classifier: License :: OSI Approved :: Apache Software License
Classifier: Programming Language :: Python :: 3
Classifier: Programming Language :: Python :: 3.11
Classifier: Programming Language :: Python :: 3.12
Requires-Dist: marisa-trie (>=1.2.0,<2.0.0)
Requires-Dist: networkx (>=3.1.0,<4.0.0)
